dewy/__init__.py
dewy/__main__.py
dewy/async_command.py
dewy/chunk/__init__.py
dewy/chunk/models.py
dewy/chunk/router.py
dewy/collection/__init__.py
dewy/collection/models.py
dewy/collection/router.py
dewy/common/__init__.py
dewy/common/collection_embeddings.py
dewy/common/db.py
dewy/common/db_migration.py
dewy/common/embeddings.py
dewy/common/extract.py
dewy/config.py
dewy/document/__init__.py
dewy/document/models.py
dewy/document/router.py
dewy/frontend/.eslintrc.js
dewy/frontend/.gitignore
dewy/frontend/README.md
dewy/frontend/dist/assets/index-a8d960f9.js
dewy/frontend/dist/favicon.ico
dewy/frontend/dist/index.html
dewy/frontend/dist/manifest.json
dewy/frontend/index.html
dewy/frontend/package-lock.json
dewy/frontend/package.json
dewy/frontend/prettier.config.js
dewy/frontend/public/favicon.ico
dewy/frontend/public/manifest.json
dewy/frontend/src/App.tsx
dewy/frontend/src/Chunk.tsx
dewy/frontend/src/Collection.tsx
dewy/frontend/src/Document.tsx
dewy/frontend/src/MyLayout.tsx
dewy/frontend/src/MyMenu.tsx
dewy/frontend/src/Search.tsx
dewy/frontend/src/data.json
dewy/frontend/src/dataProvider.ts
dewy/frontend/src/index.tsx
dewy/frontend/src/vite-env.d.ts
dewy/frontend/tsconfig.json
dewy/frontend/vite.config.ts
dewy/main.py
dewy/migration.py
dewy/migrations/0001_schema.sql
dewy/migrations/0002_document_text.sql
dewy/migrations/0003_cascade_delete.sql
dewy/routes.py
dewy/serve.py
dewy-0.4.0.dist-info/LICENSE
dewy-0.4.0.dist-info/METADATA
dewy-0.4.0.dist-info/WHEEL
dewy-0.4.0.dist-info/entry_points.txt
dewy-0.4.0.dist-info/RECORD
