Metadata-Version: 2.1
Name: dewy
Version: 0.4.0
Summary: Knowledge base service.
License: Apache-2.0
Author: Ben Chambers
Author-email: ben.chambers@datastax.com
Requires-Python: >=3.11,<3.12
Classifier: License :: OSI Approved :: Apache Software License
Classifier: Programming Language :: Python :: 3
Classifier: Programming Language :: Python :: 3.11
Requires-Dist: accelerate (>=0.26.1,<0.27.0)
Requires-Dist: asyncpg (>=0.29.0,<0.30.0)
Requires-Dist: click (>=8.1.7,<9.0.0)
Requires-Dist: docx (>=0.2.4,<0.3.0)
Requires-Dist: fastapi (>=0.108.0,<0.109.0)
Requires-Dist: langchain (>=0.1.9,<0.2.0)
Requires-Dist: langchain-community (>=0.0.24,<0.0.25)
Requires-Dist: langchain-core (>=0.1.27,<0.2.0)
Requires-Dist: langchain-openai (>=0.0.8,<0.0.9)
Requires-Dist: llama-index (>=0.9.28,<0.10.0)
Requires-Dist: loguru (>=0.7.2,<0.8.0)
Requires-Dist: markdown (>=3.5.2,<4.0.0)
Requires-Dist: numpy (>=1.26.3,<2.0.0)
Requires-Dist: pgvector (>=0.2.4,<0.3.0)
Requires-Dist: pydantic (>=2.5.3,<3.0.0)
Requires-Dist: pydantic-settings (>=2.1.0,<3.0.0)
Requires-Dist: pymupdf (>=1.23.8,<2.0.0)
Requires-Dist: python-multipart (>=0.0.7,<0.0.8)
Requires-Dist: safetensors (>=0.4.1,<0.5.0)
Requires-Dist: sentence-transformers (>=2.5.0,<3.0.0)
Requires-Dist: transformers (>=4.37.1,<5.0.0)
Requires-Dist: unstructured[doc,docx,html,md,pdf] (>=0.12.5,<0.13.0)
Requires-Dist: uvicorn (>=0.25.0,<0.26.0)
